dir/__init__.py
dir/intran.py
random11-0.0.1.dist-info/METADATA
random11-0.0.1.dist-info/WHEEL
random11-0.0.1.dist-info/top_level.txt
random11-0.0.1.dist-info/RECORD
